[{"website": "https://rap.psu.edu/recommended-academic-plan-communications-corporate-communications-option-brandywine", "classes": ["Quantification (GQ)", "3", "PSYCH 100 (GS) or SOC 001 (GS)", "3", "ENGL 015 (GWS) or ENGL 030 (GWS)", "3", "COMM 100S (GS)", "3", "COMM 160", "1", "Other Cultures", "3"], "semester": "Semester 1"}, {"website": "https://rap.psu.edu/recommended-academic-plan-communications-corporate-communications-option-brandywine", "classes": ["CAS 100 (GWS)", "3", "Arts (GA)", "3", "Health and Physical Activity (GHA)", "1.5", "Math 21 or Quantification (GQ", "3-4", "Foreign Language", "6"], "semester": "Semester 2"}, {"website": "https://rap.psu.edu/recommended-academic-plan-communications-corporate-communications-option-brandywine", "classes": ["Foreign Language", "6", "PHIL 103 (GH) or Humanities (GH)", "3", "CAS 201 (GH) or CAS 202 (GS)", "3", "COMM 270", "3", "Arts (GA)", "3"], "semester": "Semester 3"}, {"website": "https://rap.psu.edu/recommended-academic-plan-communications-corporate-communications-option-brandywine", "classes": ["BA Elective", "3", "ENGL 202 (GWS) or Elective", "3", "COMM 260W", "3", "US or IL", "3", "Communications Research Methods Course", "3"], "semester": "Semester 4"}, {"website": "https://rap.psu.edu/recommended-academic-plan-communications-corporate-communications-option-brandywine", "classes": ["CAS 252", "3", "Natural Sciences (GN)", "3", "BA Elective", "3", "COMM 370", "3", "Health and Physical Activity (GHA)", "1.5", "MKTG 301", "3"], "semester": "Semester 5"}, {"website": "https://rap.psu.edu/recommended-academic-plan-communications-corporate-communications-option-brandywine", "classes": ["Communications Elective", "3", "BA Elective", "3", "Natural Sciences (GN)", "3", "Communications Elective", "3", "US or IL", "3"], "semester": "Semester 6"}, {"website": "https://rap.psu.edu/recommended-academic-plan-communications-corporate-communications-option-brandywine", "classes": ["COMM 495 Internship or Communications Elective", "3", "Natural Sciences (GN)", "3", "Communications Elective (400 Level)", "3", "BA Elective", "3", "Communications Elective", "3"], "semester": "Semester 7"}, {"website": "https://rap.psu.edu/recommended-academic-plan-communications-corporate-communications-option-brandywine", "classes": ["COMM 495 Internship or Communications Elective", "3", "COMM 471", "3", "COMM 494", "3", "Elective", "3"], "semester": "Semester 8"}]