[{"classes": ["ENGL 015", "3", "MATH 110", "4", "ECON 102", "3", "General Education Humanities", "3", "General Education Natural Sciences", "3"], "website": "https://rap.psu.edu/bs-marketing-recommended-academic-plan-world-campus", "semester": "Stage 1\u2014Build Foundations"}, {"classes": ["CAS 100", "3", "STAT 200", "4", "MGMT 301", "3", "General Education Arts", "3", "General Education Health and Physical Activity", "3"], "website": "https://rap.psu.edu/bs-marketing-recommended-academic-plan-world-campus", "semester": "Stage 2\u2014Build Foundations"}, {"classes": ["ACCTG 211", "4", "MKTG 301W", "3", "General Education Arts", "3", "General Education Humanities", "3", "General Education Social and Behavioral Sciences", "3"], "website": "https://rap.psu.edu/bs-marketing-recommended-academic-plan-world-campus", "semester": "Stage 3--Formulate Understanding"}, {"classes": ["ENGL 202D", "3", "FIN 301", "3", "MIS 204", "3", "General Education Natural Sciences", "3", "Non-Business Elective", "2"], "website": "https://rap.psu.edu/bs-marketing-recommended-academic-plan-world-campus", "semester": "Stage 4--Formulate Understanding"}, {"classes": ["MKTG 330", "3", "SCM 301", "3", "B A 243", "4", "ECON 104", "3", "General Education Natural Sciences", "3"], "website": "https://rap.psu.edu/bs-marketing-recommended-academic-plan-world-campus", "semester": "Stage 5--Generate Expertise"}, {"classes": ["MKTG 342", "3", "MIS 390", "3", "Select 3 credits from: or MKTG 302 or MKTG 327 or MKTG 422 or MKTG 445 or MKTG 476 or MKTG 478 or MKTG 485", "3", "Non-Business Elective", "3"], "website": "https://rap.psu.edu/bs-marketing-recommended-academic-plan-world-campus", "semester": "Stage 6--Generate Expertise"}, {"classes": ["B A 364Y", "3", "Choose 6 credits from: or MKTG 302 or MKTG 327 or MKTG 422 or MKTG 445 or MKTG 476 or MKTG 478 or MKTG 485", "6", "200-400 Level Business Elective", "6"], "website": "https://rap.psu.edu/bs-marketing-recommended-academic-plan-world-campus", "semester": "Stage 7--Achieve Your Goals"}, {"classes": ["B A 462", "3", "MKTG 450W", "3", "Non-Business Elective", "3", "200-400 Level Business Elective", "6"], "website": "https://rap.psu.edu/bs-marketing-recommended-academic-plan-world-campus", "semester": "Stage 8--Achieve Your Goals"}]