[{"semester": "Semester 1", "classes": ["CRIMJ 100", "3", "ENGL 015", "3", "CAS 100", "3", "Art (GA) or Humanities (GH) or Social Science (GS)ART", "3", "Quantification (GQ)Quantification", "3", "PSU 008", "1"], "website": "https://rap.psu.edu/baccalaureate-administration-justice-ajscc-shenango"}, {"semester": "Semester 2", "classes": ["CRIMJ 012", "3", "CRIMJ 221", "3", "Art", "3", "Art (GA) or Humanities (GH) or Social Science (GS)ART", "3", "Natural Science (GN)Natural Science (GN)", "3", "Health and Physical Activity (GHA)Health and Physical Activity", "1.5"], "website": "https://rap.psu.edu/baccalaureate-administration-justice-ajscc-shenango"}, {"semester": "Semester 3", "classes": ["CRIMJ", "3", "consultation with advisor", "3", "Art", "3", "Art", "3", "Health and Physicial Activity", "1.5", "ElectiveElective", "3"], "website": "https://rap.psu.edu/baccalaureate-administration-justice-ajscc-shenango"}, {"semester": "Semester 4", "classes": ["CRIMJ Selection", "3", "STAT 200", "4", "ENGL 202 (GWS) Effective WritingValues and Ethics", "3", "Values and Ethics Course", "3", "Natural Science (GN)Natural Science", "3"], "website": "https://rap.psu.edu/baccalaureate-administration-justice-ajscc-shenango"}, {"semester": "Semester 5", "classes": ["CRIMJ", "3", "CRIMJ Selection", "3", "Consultation w/Advisor", "3", "Consultation w/Advisor", "4", "ElectiveElective", "3"], "website": "https://rap.psu.edu/baccalaureate-administration-justice-ajscc-shenango"}, {"semester": "Semester 6", "classes": ["CRIMJ", "3", "Natural Science w/lab (GN)Natural Science w/lab", "4", "Consultation w/Advisor", "3", "CRIMJ 451 or CRIMJ 453", "3", "ElectiveElective", "3"], "website": "https://rap.psu.edu/baccalaureate-administration-justice-ajscc-shenango"}, {"semester": "Semester 7", "classes": ["CRIMJ", "3", "CRIMJ 290", "1", "CRIMJ 240W", "4", "Art (GA) or Humanities (GH) or Social Science (GS)Art", "3", "ElectiveElective", "3"], "website": "https://rap.psu.edu/baccalaureate-administration-justice-ajscc-shenango"}, {"semester": "Semester 8", "classes": ["CRIMJ 494", "5", "CRIMJ 495", "5", "ElectiveElective", "3"], "website": "https://rap.psu.edu/baccalaureate-administration-justice-ajscc-shenango"}]